{"error": 0.4935, "samples": 176, "value": [98.0, 78.0], "label": "X[8] <= 36.50", "type": "split", "children": [{"error": 0.1956, "samples": 91, "value": [81.0, 10.0], "label": "X[1] <= 17.50", "type": "split", "children": [{"error": 0.0917, "samples": 83, "value": [79.0, 4.0], "label": "X[0] <= 73.50", "type": "split", "children": [{"error": 0.0487, "samples": 80, "value": [78.0, 2.0], "label": "X[4] <= 63.50", "type": "split", "children": [{"error": 0.0000, "samples": 77, "value": [77.0, 0.0], "label": "Leaf - 4", "type": "leaf"}, {"error": 0.4444, "samples": 3, "value": [1.0, 2.0], "label": "X[6] <= 69.50", "type": "split", "children": [{"error": 0.0000, "samples": 2, "value": [0.0, 2.0], "label": "Leaf - 6", "type": "leaf"}, {"error": 0.0000, "samples": 1, "value": [1.0, 0.0], "label": "Leaf - 7", "type": "leaf"}]}]}, {"error": 0.4444, "samples": 3, "value": [1.0, 2.0], "label": "X[6] <= 73.00", "type": "split", "children": [{"error": 0.0000, "samples": 2, "value": [0.0, 2.0], "label": "Leaf - 9", "type": "leaf"}, {"error": 0.0000, "samples": 1, "value": [1.0, 0.0], "label": "Leaf - 10", "type": "leaf"}]}]}, {"error": 0.3750, "samples": 8, "value": [2.0, 6.0], "label": "X[2] <= 7.50", "type": "split", "children": [{"error": 0.4444, "samples": 3, "value": [2.0, 1.0], "label": "X[4] <= 61.00", "type": "split", "children": [{"error": 0.0000, "samples": 2, "value": [2.0, 0.0], "label": "Leaf - 13", "type": "leaf"}, {"error": 0.0000, "samples": 1, "value": [0.0, 1.0], "label": "Leaf - 14", "type": "leaf"}]}, {"error": 0.0000, "samples": 5, "value": [0.0, 5.0], "label": "Leaf - 15", "type": "leaf"}]}]}, {"error": 0.3200, "samples": 85, "value": [17.0, 68.0], "label": "X[3] <= 67.50", "type": "split", "children": [{"error": 0.4550, "samples": 20, "value": [13.0, 7.0], "label": "X[7] <= 56.00", "type": "split", "children": [{"error": 0.2311, "samples": 15, "value": [13.0, 2.0], "label": "X[10] <= 5.00", "type": "split", "children": [{"error": 0.4444, "samples": 3, "value": [1.0, 2.0], "label": "X[4] <= 47.50", "type": "split", "children": [{"error": 0.0000, "samples": 1, "value": [1.0, 0.0], "label": "Leaf - 20", "type": "leaf"}, {"error": 0.0000, "samples": 2, "value": [0.0, 2.0], "label": "Leaf - 21", "type": "leaf"}]}, {"error": 0.0000, "samples": 12, "value": [12.0, 0.0], "label": "Leaf - 22", "type": "leaf"}]}, {"error": 0.0000, "samples": 5, "value": [0.0, 5.0], "label": "Leaf - 23", "type": "leaf"}]}, {"error": 0.1155, "samples": 65, "value": [4.0, 61.0], "label": "X[2] <= 6.50", "type": "split", "children": [{"error": 0.0000, "samples": 51, "value": [0.0, 51.0], "label": "Leaf - 25", "type": "leaf"}, {"error": 0.4082, "samples": 14, "value": [4.0, 10.0], "label": "X[3] <= 73.00", "type": "split", "children": [{"error": 0.4800, "samples": 5, "value": [3.0, 2.0], "label": "X[1] <= 4.50", "type": "split", "children": [{"error": 0.0000, "samples": 2, "value": [0.0, 2.0], "label": "Leaf - 28", "type": "leaf"}, {"error": 0.0000, "samples": 3, "value": [3.0, 0.0], "label": "Leaf - 29", "type": "leaf"}]}, {"error": 0.1975, "samples": 9, "value": [1.0, 8.0], "label": "X[7] <= 28.50", "type": "split", "children": [{"error": 0.0000, "samples": 1, "value": [1.0, 0.0], "label": "Leaf - 31", "type": "leaf"}, {"error": 0.0000, "samples": 8, "value": [0.0, 8.0], "label": "Leaf - 32", "type": "leaf"}]}]}]}]}]}