{"error": 0.4506, "samples": 35, "value": [23.0, 12.0], "label": "X[8] <= 40.00", "type": "split", "children": [{"error": 0.1472, "samples": 25, "value": [23.0, 2.0], "label": "X[3] <= 81.50", "type": "split", "children": [{"error": 0.0799, "samples": 24, "value": [23.0, 1.0], "label": "X[10] <= 49.00", "type": "split", "children": [{"error": 0.0000, "samples": 22, "value": [22.0, 0.0], "label": "Leaf - 3", "type": "leaf"}, {"error": 0.5000, "samples": 2, "value": [1.0, 1.0], "label": "X[7] <= 41.50", "type": "split", "children": [{"error": 0.0000, "samples": 1, "value": [1.0, 0.0], "label": "Leaf - 5", "type": "leaf"}, {"error": 0.0000, "samples": 1, "value": [0.0, 1.0], "label": "Leaf - 6", "type": "leaf"}]}]}, {"error": 0.0000, "samples": 1, "value": [0.0, 1.0], "label": "Leaf - 7", "type": "leaf"}]}, {"error": 0.0000, "samples": 10, "value": [0.0, 10.0], "label": "Leaf - 8", "type": "leaf"}]}